storeadddddddasdfads/__init__.py
storeadddddddasdfads/pp.py
hhhhhhhhhhhhhhhhhhhhh-12.0.9.dist-info/LICENSE
hhhhhhhhhhhhhhhhhhhhh-12.0.9.dist-info/METADATA
hhhhhhhhhhhhhhhhhhhhh-12.0.9.dist-info/WHEEL
hhhhhhhhhhhhhhhhhhhhh-12.0.9.dist-info/top_level.txt
hhhhhhhhhhhhhhhhhhhhh-12.0.9.dist-info/RECORD
